mplheatmap.py
mplheatmap-0.1.0.dist-info/LICENSE.txt
mplheatmap-0.1.0.dist-info/METADATA
mplheatmap-0.1.0.dist-info/WHEEL
mplheatmap-0.1.0.dist-info/top_level.txt
mplheatmap-0.1.0.dist-info/RECORD
